{
  "attributes": [
    {
      "allow_nil?": false,
      "default": "fragment(\"gen_random_uuid()\")",
      "generated?": false,
      "primary_key?": true,
      "references": null,
      "size": null,
      "source": "id",
      "type": "uuid"
    },
    {
      "allow_nil?": true,
      "default": "nil",
      "generated?": false,
      "primary_key?": false,
      "references": null,
      "size": null,
      "source": "domain",
      "type": "text"
    }
  ],
  "base_filter": null,
  "check_constraints": [],
  "custom_indexes": [],
  "custom_statements": [],
  "has_create_action": true,
  "hash": "FBB3D2FAE2F28485A0766107B5769BD54EC86590440FF09EA191535EA37794EF",
  "identities": [],
  "multitenancy": {
    "attribute": null,
    "global": null,
    "strategy": null
  },
  "repo": "Elixir.AutomatedAgency.Repo",
  "schema": null,
  "table": "domains"
}